switchbot/__init__.py
switchbot/client.py
switchbot/devices.py
switchbot/remotes.py
switchbot/scene.py
python_switchbot-2.3.1.dist-info/LICENSE
python_switchbot-2.3.1.dist-info/METADATA
python_switchbot-2.3.1.dist-info/WHEEL
python_switchbot-2.3.1.dist-info/top_level.txt
python_switchbot-2.3.1.dist-info/RECORD
