Metadata-Version: 2.1
Name: python-switchbot
Version: 2.3.1
Summary: A Python library to control SwitchBot devices connected to SwitchBot Hub
Home-page: https://github.com/jonghwanhyeon/python-switchbot
Author: Jonghwan Hyeon
Author-email: jonghwanhyeon93@gmail.com
License: MIT
Keywords: switchbot
Classifier: Development Status :: 4 - Beta
Classifier: License :: OSI Approved :: MIT License
Classifier: Programming Language :: Python :: 3
Classifier: Programming Language :: Python :: 3 :: Only
Classifier: Topic :: Home Automation
Requires-Python: >=3.7
License-File: LICENSE
Requires-Dist: requests
Requires-Dist: pyhumps
